[
    {
        "alternate_titles": [],
        "description": "<p><em>Animal Art Studio</em> is an educational game for children ages three to six. With the help of friendly animals, the player builds preschool and basic computing skills. The game is played with the mouse and contains the following four activities:</p>\n<ul>\n<li><strong>Shimmering Ocean:</strong> Four sea creatures have to be uncovered by clicking on tiles.</li>\n<li><strong>Animal Parade:</strong> By matching colours, patterns and shapes the music changes.</li>\n<li><strong>Savannah Diorama:</strong> The player can create its own animals and design its savannah habitat.</li>\n<li><strong>Rainforest Paint:</strong> A colouring books where the player mixes colours to bring the rainforest to live.</li>\n</ul>",
        "genres": [
            {
                "category": {
                    "id": 1,
                    "name": "Basic Genres"
                },
                "description": null,
                "id": 12,
                "name": "Educational"
            },
            {
                "category": {
                    "id": 4,
                    "name": "Gameplay"
                },
                "description": null,
                "id": 30,
                "name": "Puzzle elements"
            },
            {
                "category": {
                    "id": 7,
                    "name": "Interface/Control"
                },
                "description": null,
                "id": 167,
                "name": "Point and select"
            },
            {
                "category": {
                    "id": 5,
                    "name": "Educational Categories"
                },
                "description": null,
                "id": 46,
                "name": "Pre-school / toddler"
            }
        ],
        "id": 122073,
        "moby_score": null,
        "moby_url": "https://www.mobygames.com/game/122073/animal-art-studio/",
        "num_votes": 0,
        "official_url": null,
        "platforms": [
            [
                {
                    "id": 188,
                    "name": "ClickStart"
                },
                "2007"
            ]
        ],
        "sample_cover": null,
        "sample_screenshots": [],
        "title": "Animal Art Studio"
    },
    {
        "alternate_titles": [],
        "description": "<p>The player goes a journey with Dora the Explorer and her friend Boots through three different activities which include matching shapes, making number or letter patterns and finding unique colors, shapes, letters and numbers. Passing the activities earns the player rainbow stars. The activities can be played in two difficulty levels.</p>",
        "genres": [
            {
                "category": {
                    "id": 1,
                    "name": "Basic Genres"
                },
                "description": null,
                "id": 12,
                "name": "Educational"
            },
            {
                "category": {
                    "id": 12,
                    "name": "Visual Presentation"
                },
                "description": null,
                "id": 131,
                "name": "2D scrolling"
            },
            {
                "category": {
                    "id": 9,
                    "name": "Pacing"
                },
                "description": null,
                "id": 15,
                "name": "Real-time"
            },
            {
                "category": {
                    "id": 4,
                    "name": "Gameplay"
                },
                "description": null,
                "id": 140,
                "name": "Mini-games"
            },
            {
                "category": {
                    "id": 7,
                    "name": "Interface/Control"
                },
                "description": null,
                "id": 168,
                "name": "Direct control"
            },
            {
                "category": {
                    "id": 5,
                    "name": "Educational Categories"
                },
                "description": null,
                "id": 43,
                "name": "Math / logic"
            },
            {
                "category": {
                    "id": 5,
                    "name": "Educational Categories"
                },
                "description": null,
                "id": 46,
                "name": "Pre-school / toddler"
            },
            {
                "category": {
                    "id": 10,
                    "name": "Setting"
                },
                "description": null,
                "id": 211,
                "name": "South America"
            },
            {
                "category": {
                    "id": 6,
                    "name": "Other Attributes"
                },
                "description": null,
                "id": 82,
                "name": "Licensed"
            }
        ],
        "id": 166067,
        "moby_score": null,
        "moby_url": "https://www.mobygames.com/game/166067/dora-the-explorer-friends-amigos/",
        "num_votes": 0,
        "official_url": null,
        "platforms": [
            [
                {
                    "id": 188,
                    "name": "ClickStart"
                },
                "2007"
            ]
        ],
        "sample_cover": null,
        "sample_screenshots": [],
        "title": "Dora the Explorer: Friends! \u00a1Amigos!"
    },
    {
        "alternate_titles": [],
        "description": "<p>The player participates in some activities in the Learning Carnival with Leap, Lily and Tag. Activities involve collecting letters or numbers, choosing specific shapes and objects. Passing the activities earns the player points which is exchanged for carnival tickets. The activities can be played in two difficulty levels.</p>",
        "genres": [
            {
                "category": {
                    "id": 1,
                    "name": "Basic Genres"
                },
                "description": null,
                "id": 12,
                "name": "Educational"
            },
            {
                "category": {
                    "id": 12,
                    "name": "Visual Presentation"
                },
                "description": null,
                "id": 131,
                "name": "2D scrolling"
            },
            {
                "category": {
                    "id": 9,
                    "name": "Pacing"
                },
                "description": null,
                "id": 15,
                "name": "Real-time"
            },
            {
                "category": {
                    "id": 4,
                    "name": "Gameplay"
                },
                "description": null,
                "id": 140,
                "name": "Mini-games"
            },
            {
                "category": {
                    "id": 7,
                    "name": "Interface/Control"
                },
                "description": null,
                "id": 168,
                "name": "Direct control"
            },
            {
                "category": {
                    "id": 5,
                    "name": "Educational Categories"
                },
                "description": null,
                "id": 43,
                "name": "Math / logic"
            },
            {
                "category": {
                    "id": 5,
                    "name": "Educational Categories"
                },
                "description": null,
                "id": 46,
                "name": "Pre-school / toddler"
            },
            {
                "category": {
                    "id": 10,
                    "name": "Setting"
                },
                "description": null,
                "id": 207,
                "name": "North America"
            }
        ],
        "id": 166068,
        "moby_score": null,
        "moby_url": "https://www.mobygames.com/game/166068/learning-carnival/",
        "num_votes": 0,
        "official_url": null,
        "platforms": [
            [
                {
                    "id": 188,
                    "name": "ClickStart"
                },
                "2007"
            ]
        ],
        "sample_cover": null,
        "sample_screenshots": [],
        "title": "Learning Carnival"
    },
    {
        "alternate_titles": [],
        "description": "<p>The player meets the Backyardigans in a land that involves samurais and pies. Three activities in the game involve number and object recognition. Passing the activities earns the player baker's hats. The activities can be played in two difficulty levels.</p>",
        "genres": [
            {
                "category": {
                    "id": 1,
                    "name": "Basic Genres"
                },
                "description": null,
                "id": 12,
                "name": "Educational"
            },
            {
                "category": {
                    "id": 12,
                    "name": "Visual Presentation"
                },
                "description": null,
                "id": 131,
                "name": "2D scrolling"
            },
            {
                "category": {
                    "id": 9,
                    "name": "Pacing"
                },
                "description": null,
                "id": 15,
                "name": "Real-time"
            },
            {
                "category": {
                    "id": 4,
                    "name": "Gameplay"
                },
                "description": null,
                "id": 140,
                "name": "Mini-games"
            },
            {
                "category": {
                    "id": 7,
                    "name": "Interface/Control"
                },
                "description": null,
                "id": 168,
                "name": "Direct control"
            },
            {
                "category": {
                    "id": 5,
                    "name": "Educational Categories"
                },
                "description": null,
                "id": 46,
                "name": "Pre-school / toddler"
            },
            {
                "category": {
                    "id": 10,
                    "name": "Setting"
                },
                "description": null,
                "id": 229,
                "name": "Japan (Modern/Futuristic)"
            }
        ],
        "id": 166070,
        "moby_score": null,
        "moby_url": "https://www.mobygames.com/game/166070/the-backyardigans-number-pie-samurai/",
        "num_votes": 0,
        "official_url": null,
        "platforms": [
            [
                {
                    "id": 188,
                    "name": "ClickStart"
                },
                "2007"
            ]
        ],
        "sample_cover": null,
        "sample_screenshots": [],
        "title": "The Backyardigans: Number Pie Samurai"
    },
    {
        "alternate_titles": [],
        "description": "<p>The Disney Princesses Ariel, Belle and Cinderella invite the player to join in their activities. Those activities in the game make use of phobics, shape placements and letters of the alphabet. Passing the activities earns the player gems. The activities can be played in two difficulty levels.</p>",
        "genres": [
            {
                "category": {
                    "id": 1,
                    "name": "Basic Genres"
                },
                "description": null,
                "id": 12,
                "name": "Educational"
            },
            {
                "category": {
                    "id": 12,
                    "name": "Visual Presentation"
                },
                "description": null,
                "id": 133,
                "name": "Fixed / flip-screen"
            },
            {
                "category": {
                    "id": 9,
                    "name": "Pacing"
                },
                "description": null,
                "id": 15,
                "name": "Real-time"
            },
            {
                "category": {
                    "id": 4,
                    "name": "Gameplay"
                },
                "description": null,
                "id": 140,
                "name": "Mini-games"
            },
            {
                "category": {
                    "id": 7,
                    "name": "Interface/Control"
                },
                "description": null,
                "id": 168,
                "name": "Direct control"
            },
            {
                "category": {
                    "id": 5,
                    "name": "Educational Categories"
                },
                "description": null,
                "id": 46,
                "name": "Pre-school / toddler"
            },
            {
                "category": {
                    "id": 5,
                    "name": "Educational Categories"
                },
                "description": null,
                "id": 44,
                "name": "Reading / writing"
            },
            {
                "category": {
                    "id": 10,
                    "name": "Setting"
                },
                "description": null,
                "id": 78,
                "name": "Fantasy"
            },
            {
                "category": {
                    "id": 6,
                    "name": "Other Attributes"
                },
                "description": null,
                "id": 82,
                "name": "Licensed"
            }
        ],
        "id": 166284,
        "moby_score": null,
        "moby_url": "https://www.mobygames.com/game/166284/disney-princess-the-love-of-letters/",
        "num_votes": 0,
        "official_url": null,
        "platforms": [
            [
                {
                    "id": 188,
                    "name": "ClickStart"
                },
                "2008"
            ]
        ],
        "sample_cover": null,
        "sample_screenshots": [],
        "title": "Disney Princess: The Love of Letters"
    },
    {
        "alternate_titles": [],
        "description": "<p>This game takes the player for an underwater learning with Nemo, Squirt and Bruce in their activities. Those activities in the game teach typing on a keyboard, shape and object identification and learning numbers and letters. Passing the activities earns the player starfishes. The activities can be played in two difficulty levels.</p>",
        "genres": [
            {
                "category": {
                    "id": 1,
                    "name": "Basic Genres"
                },
                "description": null,
                "id": 12,
                "name": "Educational"
            },
            {
                "category": {
                    "id": 12,
                    "name": "Visual Presentation"
                },
                "description": null,
                "id": 133,
                "name": "Fixed / flip-screen"
            },
            {
                "category": {
                    "id": 9,
                    "name": "Pacing"
                },
                "description": null,
                "id": 15,
                "name": "Real-time"
            },
            {
                "category": {
                    "id": 4,
                    "name": "Gameplay"
                },
                "description": null,
                "id": 140,
                "name": "Mini-games"
            },
            {
                "category": {
                    "id": 7,
                    "name": "Interface/Control"
                },
                "description": null,
                "id": 168,
                "name": "Direct control"
            },
            {
                "category": {
                    "id": 5,
                    "name": "Educational Categories"
                },
                "description": null,
                "id": 46,
                "name": "Pre-school / toddler"
            },
            {
                "category": {
                    "id": 5,
                    "name": "Educational Categories"
                },
                "description": null,
                "id": 44,
                "name": "Reading / writing"
            },
            {
                "category": {
                    "id": 5,
                    "name": "Educational Categories"
                },
                "description": null,
                "id": 45,
                "name": "Typing"
            },
            {
                "category": {
                    "id": 10,
                    "name": "Setting"
                },
                "description": null,
                "id": 208,
                "name": "Oceania"
            },
            {
                "category": {
                    "id": 6,
                    "name": "Other Attributes"
                },
                "description": null,
                "id": 82,
                "name": "Licensed"
            }
        ],
        "id": 166313,
        "moby_score": null,
        "moby_url": "https://www.mobygames.com/game/166313/finding-nemo-sea-of-keys/",
        "num_votes": 0,
        "official_url": null,
        "platforms": [
            [
                {
                    "id": 188,
                    "name": "ClickStart"
                },
                "2007"
            ]
        ],
        "sample_cover": null,
        "sample_screenshots": [],
        "title": "Finding Nemo: Sea of Keys"
    },
    {
        "alternate_titles": [],
        "description": "<p>In the Tri-County Area, player is set for a learning experience with Woody, Buzz and Jessie. Their activities involve doing math, counting objects and number sequences. Passing the activities earns the player aliens. The activities can be played in two difficulty levels.</p>",
        "genres": [
            {
                "category": {
                    "id": 1,
                    "name": "Basic Genres"
                },
                "description": null,
                "id": 12,
                "name": "Educational"
            },
            {
                "category": {
                    "id": 12,
                    "name": "Visual Presentation"
                },
                "description": null,
                "id": 131,
                "name": "2D scrolling"
            },
            {
                "category": {
                    "id": 9,
                    "name": "Pacing"
                },
                "description": null,
                "id": 15,
                "name": "Real-time"
            },
            {
                "category": {
                    "id": 4,
                    "name": "Gameplay"
                },
                "description": null,
                "id": 140,
                "name": "Mini-games"
            },
            {
                "category": {
                    "id": 7,
                    "name": "Interface/Control"
                },
                "description": null,
                "id": 168,
                "name": "Direct control"
            },
            {
                "category": {
                    "id": 5,
                    "name": "Educational Categories"
                },
                "description": null,
                "id": 43,
                "name": "Math / logic"
            },
            {
                "category": {
                    "id": 10,
                    "name": "Setting"
                },
                "description": null,
                "id": 207,
                "name": "North America"
            },
            {
                "category": {
                    "id": 6,
                    "name": "Other Attributes"
                },
                "description": null,
                "id": 82,
                "name": "Licensed"
            }
        ],
        "id": 166314,
        "moby_score": null,
        "moby_url": "https://www.mobygames.com/game/166314/toy-story-to-100-and-beyond/",
        "num_votes": 0,
        "official_url": null,
        "platforms": [
            [
                {
                    "id": 188,
                    "name": "ClickStart"
                },
                "2007"
            ]
        ],
        "sample_cover": null,
        "sample_screenshots": [],
        "title": "Toy Story: To 100 and Beyond!"
    },
    {
        "alternate_titles": [],
        "description": "<p>On the Island of Sodor, the player joins Thomas the Tank Engine and his friends in three different activities. The activities in the game are about letters, number sequences and logic. Passing the activities earns the player train tickers. The activities can be played in two difficulty levels.</p>",
        "genres": [
            {
                "category": {
                    "id": 1,
                    "name": "Basic Genres"
                },
                "description": null,
                "id": 12,
                "name": "Educational"
            },
            {
                "category": {
                    "id": 2,
                    "name": "Perspective"
                },
                "description": null,
                "id": 129,
                "name": "Diagonal-down"
            },
            {
                "category": {
                    "id": 2,
                    "name": "Perspective"
                },
                "description": null,
                "id": 17,
                "name": "Side view"
            },
            {
                "category": {
                    "id": 12,
                    "name": "Visual Presentation"
                },
                "description": null,
                "id": 131,
                "name": "2D scrolling"
            },
            {
                "category": {
                    "id": 9,
                    "name": "Pacing"
                },
                "description": null,
                "id": 15,
                "name": "Real-time"
            },
            {
                "category": {
                    "id": 4,
                    "name": "Gameplay"
                },
                "description": null,
                "id": 140,
                "name": "Mini-games"
            },
            {
                "category": {
                    "id": 7,
                    "name": "Interface/Control"
                },
                "description": null,
                "id": 168,
                "name": "Direct control"
            },
            {
                "category": {
                    "id": 5,
                    "name": "Educational Categories"
                },
                "description": null,
                "id": 43,
                "name": "Math / logic"
            },
            {
                "category": {
                    "id": 5,
                    "name": "Educational Categories"
                },
                "description": null,
                "id": 44,
                "name": "Reading / writing"
            },
            {
                "category": {
                    "id": 10,
                    "name": "Setting"
                },
                "description": null,
                "id": 202,
                "name": "Europe"
            },
            {
                "category": {
                    "id": 6,
                    "name": "Other Attributes"
                },
                "description": null,
                "id": 82,
                "name": "Licensed"
            }
        ],
        "id": 166327,
        "moby_score": null,
        "moby_url": "https://www.mobygames.com/game/166327/thomas-friends-learning-destinations/",
        "num_votes": 0,
        "official_url": null,
        "platforms": [
            [
                {
                    "id": 188,
                    "name": "ClickStart"
                },
                "2007"
            ]
        ],
        "sample_cover": null,
        "sample_screenshots": [],
        "title": "Thomas & Friends: Learning Destinations"
    },
    {
        "alternate_titles": [],
        "description": "<p>The player goes to Radiator Springs where Lightning McQueen, Mater and Flo are engaged in four different activities. The activities are made up counting, number sequences, letter learning and colors. Passing the activities earns the player hubcaps. The activities can be played in two difficulty levels.</p>",
        "genres": [
            {
                "category": {
                    "id": 1,
                    "name": "Basic Genres"
                },
                "description": null,
                "id": 12,
                "name": "Educational"
            },
            {
                "category": {
                    "id": 2,
                    "name": "Perspective"
                },
                "description": null,
                "id": 17,
                "name": "Side view"
            },
            {
                "category": {
                    "id": 2,
                    "name": "Perspective"
                },
                "description": null,
                "id": 13,
                "name": "Top-down"
            },
            {
                "category": {
                    "id": 12,
                    "name": "Visual Presentation"
                },
                "description": null,
                "id": 133,
                "name": "Fixed / flip-screen"
            },
            {
                "category": {
                    "id": 9,
                    "name": "Pacing"
                },
                "description": null,
                "id": 15,
                "name": "Real-time"
            },
            {
                "category": {
                    "id": 4,
                    "name": "Gameplay"
                },
                "description": null,
                "id": 140,
                "name": "Mini-games"
            },
            {
                "category": {
                    "id": 7,
                    "name": "Interface/Control"
                },
                "description": null,
                "id": 168,
                "name": "Direct control"
            },
            {
                "category": {
                    "id": 5,
                    "name": "Educational Categories"
                },
                "description": null,
                "id": 43,
                "name": "Math / logic"
            },
            {
                "category": {
                    "id": 5,
                    "name": "Educational Categories"
                },
                "description": null,
                "id": 44,
                "name": "Reading / writing"
            },
            {
                "category": {
                    "id": 10,
                    "name": "Setting"
                },
                "description": null,
                "id": 207,
                "name": "North America"
            },
            {
                "category": {
                    "id": 6,
                    "name": "Other Attributes"
                },
                "description": null,
                "id": 82,
                "name": "Licensed"
            }
        ],
        "id": 166333,
        "moby_score": null,
        "moby_url": "https://www.mobygames.com/game/166333/cars-the-road-to-learning/",
        "num_votes": 0,
        "official_url": null,
        "platforms": [
            [
                {
                    "id": 188,
                    "name": "ClickStart"
                },
                "2008"
            ]
        ],
        "sample_cover": null,
        "sample_screenshots": [],
        "title": "Cars: The Road to Learning!"
    },
    {
        "alternate_titles": [],
        "description": "<p>This game expands content and mini games of the original <em>My First Computer</em> found on the Clickstart. Players can adopt a puppy of their very own and play five different activities with him/her. In between virtual care and play with the puppy, the player also picks up on learning about letters, phonics and numbers. Passing the activities earns the player coins, which can be used to purchase accessories for the puppy. The activities can be played in two difficulty levels.</p>",
        "genres": [
            {
                "category": {
                    "id": 1,
                    "name": "Basic Genres"
                },
                "description": null,
                "id": 12,
                "name": "Educational"
            },
            {
                "category": {
                    "id": 2,
                    "name": "Perspective"
                },
                "description": null,
                "id": 126,
                "name": "3rd-person (Other)"
            },
            {
                "category": {
                    "id": 12,
                    "name": "Visual Presentation"
                },
                "description": null,
                "id": 131,
                "name": "2D scrolling"
            },
            {
                "category": {
                    "id": 9,
                    "name": "Pacing"
                },
                "description": null,
                "id": 15,
                "name": "Real-time"
            },
            {
                "category": {
                    "id": 4,
                    "name": "Gameplay"
                },
                "description": null,
                "id": 140,
                "name": "Mini-games"
            },
            {
                "category": {
                    "id": 7,
                    "name": "Interface/Control"
                },
                "description": null,
                "id": 168,
                "name": "Direct control"
            },
            {
                "category": {
                    "id": 5,
                    "name": "Educational Categories"
                },
                "description": null,
                "id": 43,
                "name": "Math / logic"
            },
            {
                "category": {
                    "id": 5,
                    "name": "Educational Categories"
                },
                "description": null,
                "id": 46,
                "name": "Pre-school / toddler"
            },
            {
                "category": {
                    "id": 5,
                    "name": "Educational Categories"
                },
                "description": null,
                "id": 44,
                "name": "Reading / writing"
            },
            {
                "category": {
                    "id": 10,
                    "name": "Setting"
                },
                "description": null,
                "id": 207,
                "name": "North America"
            }
        ],
        "id": 166549,
        "moby_score": null,
        "moby_url": "https://www.mobygames.com/game/166549/scouts-puppy-pal/",
        "num_votes": 0,
        "official_url": null,
        "platforms": [
            [
                {
                    "id": 188,
                    "name": "ClickStart"
                },
                "2008"
            ]
        ],
        "sample_cover": null,
        "sample_screenshots": [],
        "title": "Scout's Puppy Pal"
    },
    {
        "alternate_titles": [],
        "description": "<p>The player goes on an expedition with Diego to aid some baby animals in the jungle, desert and other places. The adventure includes six activities that teach players how to effectively use a keyboard and mouse, numbers, counting, sequences, letters and shapes. Passing the activities earns the player paw points. The activities can be played in two difficulty levels.</p>",
        "genres": [
            {
                "category": {
                    "id": 1,
                    "name": "Basic Genres"
                },
                "description": null,
                "id": 12,
                "name": "Educational"
            },
            {
                "category": {
                    "id": 2,
                    "name": "Perspective"
                },
                "description": null,
                "id": 126,
                "name": "3rd-person (Other)"
            },
            {
                "category": {
                    "id": 12,
                    "name": "Visual Presentation"
                },
                "description": null,
                "id": 131,
                "name": "2D scrolling"
            },
            {
                "category": {
                    "id": 9,
                    "name": "Pacing"
                },
                "description": null,
                "id": 15,
                "name": "Real-time"
            },
            {
                "category": {
                    "id": 4,
                    "name": "Gameplay"
                },
                "description": null,
                "id": 140,
                "name": "Mini-games"
            },
            {
                "category": {
                    "id": 7,
                    "name": "Interface/Control"
                },
                "description": null,
                "id": 168,
                "name": "Direct control"
            },
            {
                "category": {
                    "id": 5,
                    "name": "Educational Categories"
                },
                "description": null,
                "id": 43,
                "name": "Math / logic"
            },
            {
                "category": {
                    "id": 5,
                    "name": "Educational Categories"
                },
                "description": null,
                "id": 46,
                "name": "Pre-school / toddler"
            },
            {
                "category": {
                    "id": 5,
                    "name": "Educational Categories"
                },
                "description": null,
                "id": 44,
                "name": "Reading / writing"
            },
            {
                "category": {
                    "id": 10,
                    "name": "Setting"
                },
                "description": null,
                "id": 211,
                "name": "South America"
            },
            {
                "category": {
                    "id": 6,
                    "name": "Other Attributes"
                },
                "description": null,
                "id": 82,
                "name": "Licensed"
            }
        ],
        "id": 166550,
        "moby_score": null,
        "moby_url": "https://www.mobygames.com/game/166550/go-diego-go-learning-expeditions/",
        "num_votes": 0,
        "official_url": null,
        "platforms": [
            [
                {
                    "id": 188,
                    "name": "ClickStart"
                },
                "2008"
            ]
        ],
        "sample_cover": null,
        "sample_screenshots": [],
        "title": "Go Diego Go!: Learning Expeditions"
    },
    {
        "alternate_titles": [],
        "description": "<p>Kai-Lan invites the player to participate in five festive activities. The activities show players the topics of basic Chinese, counting, early math, letters and colors. Passing the activities earns the player lit sparklers. The activities can be played in two difficulty levels.</p>",
        "genres": [
            {
                "category": {
                    "id": 1,
                    "name": "Basic Genres"
                },
                "description": null,
                "id": 12,
                "name": "Educational"
            },
            {
                "category": {
                    "id": 2,
                    "name": "Perspective"
                },
                "description": null,
                "id": 126,
                "name": "3rd-person (Other)"
            },
            {
                "category": {
                    "id": 12,
                    "name": "Visual Presentation"
                },
                "description": null,
                "id": 133,
                "name": "Fixed / flip-screen"
            },
            {
                "category": {
                    "id": 9,
                    "name": "Pacing"
                },
                "description": null,
                "id": 15,
                "name": "Real-time"
            },
            {
                "category": {
                    "id": 4,
                    "name": "Gameplay"
                },
                "description": null,
                "id": 140,
                "name": "Mini-games"
            },
            {
                "category": {
                    "id": 7,
                    "name": "Interface/Control"
                },
                "description": null,
                "id": 168,
                "name": "Direct control"
            },
            {
                "category": {
                    "id": 5,
                    "name": "Educational Categories"
                },
                "description": null,
                "id": 43,
                "name": "Math / logic"
            },
            {
                "category": {
                    "id": 5,
                    "name": "Educational Categories"
                },
                "description": null,
                "id": 44,
                "name": "Reading / writing"
            },
            {
                "category": {
                    "id": 10,
                    "name": "Setting"
                },
                "description": null,
                "id": 197,
                "name": "Asia"
            },
            {
                "category": {
                    "id": 6,
                    "name": "Other Attributes"
                },
                "description": null,
                "id": 82,
                "name": "Licensed"
            }
        ],
        "id": 166557,
        "moby_score": null,
        "moby_url": "https://www.mobygames.com/game/166557/ni-hao-kai-lan/",
        "num_votes": 0,
        "official_url": null,
        "platforms": [
            [
                {
                    "id": 188,
                    "name": "ClickStart"
                },
                "2008"
            ]
        ],
        "sample_cover": null,
        "sample_screenshots": [],
        "title": "Ni Hao, Kai-Lan"
    },
    {
        "alternate_titles": [],
        "description": "<p>Bob and the Crew invite the player to help out in three playable activities. The activities encompass skills in letters, phonics, shapes and a musical bonus activity. Passing the activities earns the player hard hats. The activities can be played in two difficulty levels.</p>",
        "genres": [
            {
                "category": {
                    "id": 1,
                    "name": "Basic Genres"
                },
                "description": null,
                "id": 12,
                "name": "Educational"
            },
            {
                "category": {
                    "id": 2,
                    "name": "Perspective"
                },
                "description": null,
                "id": 126,
                "name": "3rd-person (Other)"
            },
            {
                "category": {
                    "id": 12,
                    "name": "Visual Presentation"
                },
                "description": null,
                "id": 133,
                "name": "Fixed / flip-screen"
            },
            {
                "category": {
                    "id": 9,
                    "name": "Pacing"
                },
                "description": null,
                "id": 15,
                "name": "Real-time"
            },
            {
                "category": {
                    "id": 4,
                    "name": "Gameplay"
                },
                "description": null,
                "id": 140,
                "name": "Mini-games"
            },
            {
                "category": {
                    "id": 7,
                    "name": "Interface/Control"
                },
                "description": null,
                "id": 168,
                "name": "Direct control"
            },
            {
                "category": {
                    "id": 5,
                    "name": "Educational Categories"
                },
                "description": null,
                "id": 59,
                "name": "Music"
            },
            {
                "category": {
                    "id": 5,
                    "name": "Educational Categories"
                },
                "description": null,
                "id": 44,
                "name": "Reading / writing"
            },
            {
                "category": {
                    "id": 10,
                    "name": "Setting"
                },
                "description": null,
                "id": 207,
                "name": "North America"
            },
            {
                "category": {
                    "id": 6,
                    "name": "Other Attributes"
                },
                "description": null,
                "id": 82,
                "name": "Licensed"
            }
        ],
        "id": 166558,
        "moby_score": null,
        "moby_url": "https://www.mobygames.com/game/166558/bob-the-builder-project-learn-it/",
        "num_votes": 0,
        "official_url": null,
        "platforms": [
            [
                {
                    "id": 188,
                    "name": "ClickStart"
                },
                "2007"
            ]
        ],
        "sample_cover": null,
        "sample_screenshots": [],
        "title": "Bob the Builder: Project: Learn It"
    },
    {
        "alternate_titles": [],
        "description": "<p>The Clickstart console comes with three different activities starring Scout, Tad and Dot. The activities teach users about numbers, letters and typing. Passing the activities earns the player dog bones, which can be used to reward Scout. Extra activities include exploring and playing in Scout's house and going to the Inbox where there are postcards to play with. The activities can be played in two difficulty levels.</p>",
        "genres": [
            {
                "category": {
                    "id": 1,
                    "name": "Basic Genres"
                },
                "description": null,
                "id": 12,
                "name": "Educational"
            },
            {
                "category": {
                    "id": 2,
                    "name": "Perspective"
                },
                "description": null,
                "id": 126,
                "name": "3rd-person (Other)"
            },
            {
                "category": {
                    "id": 12,
                    "name": "Visual Presentation"
                },
                "description": null,
                "id": 131,
                "name": "2D scrolling"
            },
            {
                "category": {
                    "id": 9,
                    "name": "Pacing"
                },
                "description": null,
                "id": 15,
                "name": "Real-time"
            },
            {
                "category": {
                    "id": 4,
                    "name": "Gameplay"
                },
                "description": null,
                "id": 140,
                "name": "Mini-games"
            },
            {
                "category": {
                    "id": 5,
                    "name": "Educational Categories"
                },
                "description": null,
                "id": 43,
                "name": "Math / logic"
            },
            {
                "category": {
                    "id": 5,
                    "name": "Educational Categories"
                },
                "description": null,
                "id": 46,
                "name": "Pre-school / toddler"
            },
            {
                "category": {
                    "id": 5,
                    "name": "Educational Categories"
                },
                "description": null,
                "id": 44,
                "name": "Reading / writing"
            },
            {
                "category": {
                    "id": 5,
                    "name": "Educational Categories"
                },
                "description": null,
                "id": 45,
                "name": "Typing"
            },
            {
                "category": {
                    "id": 10,
                    "name": "Setting"
                },
                "description": null,
                "id": 207,
                "name": "North America"
            }
        ],
        "id": 166559,
        "moby_score": null,
        "moby_url": "https://www.mobygames.com/game/166559/my-first-computer/",
        "num_votes": 0,
        "official_url": null,
        "platforms": [
            [
                {
                    "id": 188,
                    "name": "ClickStart"
                },
                "2007"
            ]
        ],
        "sample_cover": null,
        "sample_screenshots": [],
        "title": "My First Computer"
    }
]